wer/__init__.py
wer/helpers.py
wer/schema.py
wer-0.1.0.dist-info/DESCRIPTION.rst
wer-0.1.0.dist-info/METADATA
wer-0.1.0.dist-info/RECORD
wer-0.1.0.dist-info/WHEEL
wer-0.1.0.dist-info/metadata.json
wer-0.1.0.dist-info/top_level.txt
